munchboka_edutools/__init__.py
munchboka_edutools/_plotmath_shim.py
munchboka_edutools/_version.py
munchboka_edutools/munchboka.code-workspace
munchboka_edutools/cli/__init__.py
munchboka_edutools/cli/build.py
munchboka_edutools/config/__init__.py
munchboka_edutools/config/profiles.py
munchboka_edutools/directives/__init__.py
munchboka_edutools/directives/admonitions.py
munchboka_edutools/directives/animate.py
munchboka_edutools/directives/cas_popup.py
munchboka_edutools/directives/clear.py
munchboka_edutools/directives/dialogue.py
munchboka_edutools/directives/escape_room.py
munchboka_edutools/directives/escape_room2.py
munchboka_edutools/directives/factor_tree.py
munchboka_edutools/directives/flashcards.py
munchboka_edutools/directives/ggb.py
munchboka_edutools/directives/ggb_icon.py
munchboka_edutools/directives/ggb_popup.py
munchboka_edutools/directives/horner.py
munchboka_edutools/directives/interactive_code.py
munchboka_edutools/directives/interactive_graph.py
munchboka_edutools/directives/jeopardy.py
munchboka_edutools/directives/jeopardy2.py
munchboka_edutools/directives/multi_interactive_graph.py
munchboka_edutools/directives/multi_plot.py
munchboka_edutools/directives/multi_plot2.py
munchboka_edutools/directives/pair_puzzle.py
munchboka_edutools/directives/parsons.py
munchboka_edutools/directives/plot.py
munchboka_edutools/directives/poly_icon.py
munchboka_edutools/directives/polydiv.py
munchboka_edutools/directives/popup.py
munchboka_edutools/directives/quiz.py
munchboka_edutools/directives/quiz2.py
munchboka_edutools/directives/signchart.py
munchboka_edutools/directives/signchart2.py
munchboka_edutools/directives/svg_delta.py
munchboka_edutools/directives/timed_quiz.py
munchboka_edutools/directives/turtle.py
munchboka_edutools/processors/__init__.py
munchboka_edutools/processors/base.py
munchboka_edutools/processors/math_rendering.py
munchboka_edutools/processors/page_breaks.py
munchboka_edutools/processors/typography.py
munchboka_edutools-0.3.12.dist-info/METADATA
munchboka_edutools-0.3.12.dist-info/WHEEL
munchboka_edutools-0.3.12.dist-info/entry_points.txt
munchboka_edutools-0.3.12.dist-info/licenses/LICENSE
munchboka_edutools-0.3.12.dist-info/RECORD
