Metadata-Version: 2.4
Name: munchboka-edutools
Version: 0.3.12
Summary: Sphinx/Jupyter Book directives and assets for Munchboka and VGS books
Project-URL: Homepage, https://github.com/reneaas/munchboka-edutools
Project-URL: Issues, https://github.com/reneaas/munchboka-edutools/issues
Author: René Ask
License: MIT License
License-File: LICENSE
Keywords: directives,education,jupyter-book,munchboka,sphinx
Classifier: Framework :: Sphinx :: Extension
Classifier: Framework :: Sphinx :: Theme
Classifier: License :: OSI Approved :: MIT License
Classifier: Programming Language :: Python :: 3
Classifier: Topic :: Documentation
Requires-Python: >=3.9
Requires-Dist: beautifulsoup4>=4.11
Requires-Dist: cairosvg>=2.7.0
Requires-Dist: click>=8.0
Requires-Dist: imageio>=2.31.0
Requires-Dist: lxml>=4.9
Requires-Dist: matplotlib>=3.7
Requires-Dist: numpy>=1.23
Requires-Dist: pillow>=10.0.0
Requires-Dist: plotmath
Requires-Dist: pyyaml>=6.0
Requires-Dist: scipy>=1.9
Requires-Dist: signchart
Requires-Dist: sphinx>=6.0
Requires-Dist: sympy>=1.11
Provides-Extra: dev
Requires-Dist: black; extra == 'dev'
Requires-Dist: build; extra == 'dev'
Requires-Dist: jupyter-book; extra == 'dev'
Requires-Dist: pytest; extra == 'dev'
Requires-Dist: ruff; extra == 'dev'
Requires-Dist: twine; extra == 'dev'
